pep8ext_naming-stubs/METADATA.toml
pep8ext_naming-stubs/__init__.pyi
pep8ext_naming-stubs/py.typed
types_pep8_naming-0.14.0.20250401.dist-info/licenses/LICENSE
types_pep8_naming-0.14.0.20250401.dist-info/METADATA
types_pep8_naming-0.14.0.20250401.dist-info/WHEEL
types_pep8_naming-0.14.0.20250401.dist-info/top_level.txt
types_pep8_naming-0.14.0.20250401.dist-info/RECORD
