Metadata-Version: 2.4
Name: types-pep8-naming
Version: 0.14.0.20250401
Summary: Typing stubs for pep8-naming
License-Expression: Apache-2.0
Project-URL: Homepage, https://github.com/python/typeshed
Project-URL: GitHub, https://github.com/python/typeshed
Project-URL: Changes, https://github.com/typeshed-internal/stub_uploader/blob/main/data/changelogs/pep8-naming.md
Project-URL: Issue tracker, https://github.com/python/typeshed/issues
Project-URL: Chat, https://gitter.im/python/typing
Classifier: Programming Language :: Python :: 3
Classifier: Typing :: Stubs Only
Requires-Python: >=3.9
License-File: LICENSE
Dynamic: license-file
